{
  "belt_system": {
    "name": "TAGB (Taekwondo Association of Great Britain)",
    "belts": [
      {
        "id": "10th_keup",
        "name": "10th Keup (White Belt)",
        "short_name": "10th Keup",
        "display_name": "White Belt",
        "color_name": "White",
        "sort_order": 15,
        "is_keup": true,
        "primary_color": "#FFFFFF",
        "secondary_color": "#F8F9FA",
        "text_color": "#000000",
        "border_color": "#E9ECEF",
        "gradient": ["#FFFFFF", "#F8F9FA"],
        "required_categories": ["basics", "numbers", "techniques", "stances"],
        "optional_categories": [],
        "description": "Foundation level focusing on basic commands, numbers, and fundamental techniques"
      },
      {
        "id": "9th_keup", 
        "name": "9th Keup (White Belt - Yellow Tag)",
        "short_name": "9th Keup",
        "display_name": "White/Yellow Tag",
        "color_name": "White/Yellow",
        "sort_order": 14,
        "is_keup": true,
        "primary_color": "#FFFFFF",
        "secondary_color": "#FFF3CD",
        "text_color": "#000000", 
        "border_color": "#FFEAA7",
        "gradient": ["#FFFFFF", "#FFF3CD"],
        "required_categories": ["basics", "techniques", "stances"],
        "optional_categories": ["blocks"],
        "description": "Building on white belt with additional techniques"
      },
      {
        "id": "8th_keup",
        "name": "8th Keup (Yellow Belt)", 
        "short_name": "8th Keup",
        "display_name": "Yellow Belt",
        "color_name": "Yellow",
        "sort_order": 13,
        "is_keup": true,
        "primary_color": "#FFC107",
        "secondary_color": "#FFF3CD",
        "text_color": "#000000",
        "border_color": "#FFEAA7", 
        "gradient": ["#FFC107", "#FFD93D"],
        "required_categories": ["techniques", "stances", "blocks"],
        "optional_categories": ["strikes"],
        "description": "Introduction to more complex techniques and combinations"
      },
      {
        "id": "7th_keup",
        "name": "7th Keup (Yellow Belt - Green Tag)",
        "short_name": "7th Keup", 
        "display_name": "Yellow/Green Tag",
        "color_name": "Yellow/Green",
        "sort_order": 12,
        "is_keup": true,
        "primary_color": "#FFC107",
        "secondary_color": "#D4F1F4",
        "text_color": "#000000",
        "border_color": "#28A745",
        "gradient": ["#FFC107", "#28A745"],
        "required_categories": ["techniques", "stances", "blocks", "strikes"],
        "optional_categories": ["kicks"],
        "description": "Transition level with increased complexity"
      },
      {
        "id": "6th_keup",
        "name": "6th Keup (Green Belt)",
        "short_name": "6th Keup",
        "display_name": "Green Belt", 
        "color_name": "Green",
        "sort_order": 11,
        "is_keup": true,
        "primary_color": "#28A745",
        "secondary_color": "#D4F1F4",
        "text_color": "#FFFFFF",
        "border_color": "#1E7E34",
        "gradient": ["#28A745", "#34CE57"],
        "required_categories": ["techniques", "stances", "blocks", "strikes", "kicks"],
        "optional_categories": ["patterns"],
        "description": "Intermediate level with comprehensive technique base"
      },
      {
        "id": "2nd_keup",
        "name": "2nd Keup (Red Belt)",
        "short_name": "2nd Keup",
        "display_name": "Red Belt",
        "color_name": "Red", 
        "sort_order": 7,
        "is_keup": true,
        "primary_color": "#DC3545",
        "secondary_color": "#F8D7DA",
        "text_color": "#FFFFFF",
        "border_color": "#C82333",
        "gradient": ["#DC3545", "#E74C3C"],
        "required_categories": ["techniques", "stances", "blocks", "strikes", "kicks", "patterns"],
        "optional_categories": ["philosophy", "titles"],
        "description": "Advanced colored belt preparing for black belt"
      },
      {
        "id": "1st_keup",
        "name": "1st Keup (Red Belt - Black Tag)",
        "short_name": "1st Keup",
        "display_name": "Red/Black Tag",
        "color_name": "Red/Black",
        "sort_order": 6,
        "is_keup": true, 
        "primary_color": "#DC3545",
        "secondary_color": "#343A40",
        "text_color": "#FFFFFF",
        "border_color": "#000000",
        "gradient": ["#DC3545", "#343A40"],
        "required_categories": ["techniques", "stances", "blocks", "strikes", "kicks", "patterns", "philosophy"],
        "optional_categories": ["titles"],
        "description": "Final colored belt before black belt testing"
      },
      {
        "id": "1st_dan",
        "name": "1st Dan (Black Belt)",
        "short_name": "1st Dan", 
        "display_name": "1st Dan Black Belt",
        "color_name": "Black",
        "sort_order": 5,
        "is_keup": false,
        "primary_color": "#000000",
        "secondary_color": "#343A40",
        "text_color": "#FFFFFF", 
        "border_color": "#FFD700",
        "gradient": ["#000000", "#343A40"],
        "required_categories": ["techniques", "stances", "blocks", "strikes", "kicks", "patterns", "philosophy", "titles"],
        "optional_categories": [],
        "description": "First degree black belt - beginning of advanced training"
      }
    ]
  }
}