{
  "version": "1.0",
  "category": "kicks",
  "description": "Comprehensive database of Taekwondo kicking techniques",
  "techniques": [
    {
      "id": "dwit_chagi",
      "names": {
        "english": "Back Kick",
        "phonetic": "/twi.tʃʰa.ɡi/",
        "romanised": "Dwit Chagi",
        "hangul": "뒤차기"
      },
      "description": "A powerful linear kick executed backwards, striking with the heel. The practitioner looks over the shoulder to aim while driving the heel straight back into the target.",
      "execution": {
        "chamber": "Lift knee to waist height while looking over shoulder",
        "strike": "Drive heel straight back into target with full hip extension",
        "retraction": "Pull foot back to chamber before placing down"
      },
      "striking_tool": {
        "hangul": "뒷축",
        "romanised": "Dwitchook",
        "english": "Back Heel",
        "phonetic": "/twit.tʃʰuk/"
      },
      "target_areas": [
        "solar plexus",
        "abdomen",
        "ribs",
        "spine"
      ],
      "applicable_stances": [
        "gunnun_sogi",
        "narani_junbi_sogi"
      ],
      "belt_levels": [
        "6th_keup",
        "5th_keup",
        "4th_keup",
        "3rd_keup",
        "2nd_keup",
        "1st_keup",
        "1st_dan",
        "2nd_dan"
      ],
      "difficulty": "intermediate",
      "tags": [
        "linear",
        "back",
        "heel",
        "powerful",
        "backwards"
      ],
      "variations": [
        "twimyo_dwit_chagi"
      ],
      "images": [
        "dwit_chagi_chamber.jpg",
        "dwit_chagi_execution.jpg",
        "dwit_chagi_heel_detail.jpg"
      ],
      "common_mistakes": [
        "Not looking over shoulder",
        "Poor hip drive",
        "Telegraphing the technique"
      ]
    },
    {
      "id": "kick_back_piercing_kick",
      "names": {
        "english": "Back Piercing Kick",
        "romanised": "Dwit Cha Jirugi",
        "hangul": "뒤 차 지르기"
      },
      "category": "kicks"
    },
    {
      "id": "kick_checking_kick",
      "names": {
        "english": "Checking Kick",
        "romanised": "Cha Mum Chagi",
        "hangul": "차 몸 차기"
      },
      "category": "kicks"
    },
    {
      "id": "kick_consecutive_kick",
      "names": {
        "english": "Consecutive Kick",
        "romanised": "Yonsok Chagi",
        "hangul": "연속 차기"
      },
      "category": "kicks"
    },
    {
      "id": "bandal_chagi",
      "names": {
        "english": "Crescent Kick",
        "phonetic": "/pan.dal.tʃʰa.ɡi/",
        "romanised": "Bandal Chagi",
        "hangul": "반달차기"
      },
      "description": "A sweeping kick that travels in a crescent or semi-circular path, typically used to strike or sweep away an opponent's guard or attack the side of the head.",
      "execution": {
        "chamber": "Lift leg straight up or to the side",
        "strike": "Sweep foot in crescent arc across body",
        "retraction": "Control descent of leg after completing arc"
      },
      "striking_tool": {
        "hangul": "발등",
        "romanised": "Baldeung",
        "english": "Instep",
        "phonetic": "/pal.dɯŋ/"
      },
      "target_areas": [
        "temple",
        "jaw",
        "arm",
        "hand",
        "weapon"
      ],
      "applicable_stances": [
        "gunnun_sogi",
        "narani_junbi_sogi"
      ],
      "belt_levels": [
        "2nd_keup",
        "1st_keup",
        "1st_dan",
        "2nd_dan"
      ],
      "difficulty": "intermediate",
      "tags": [
        "crescent",
        "sweeping",
        "circular",
        "deflection"
      ],
      "variations": [
        "anuro_bandal_chagi",
        "bakuro_bandal_chagi"
      ],
      "images": [
        "bandal_chagi_start.jpg",
        "bandal_chagi_arc.jpg",
        "bandal_chagi_finish.jpg"
      ],
      "common_mistakes": [
        "Poor arc control",
        "Wrong striking surface",
        "Loss of balance"
      ]
    },
    {
      "id": "kick_dodging_reverse_turning_kick",
      "names": {
        "english": "Dodging Reverse Turning Kick",
        "romanised": "Pihamyo Bandae Dollyo Chagi",
        "hangul": "피하며 반대 돌려 차기"
      },
      "category": "kicks"
    },
    {
      "id": "naeryo_chagi",
      "names": {
        "english": "Downward Kick",
        "phonetic": "/ne.ɾjʌ.tʃʰa.ɡi/",
        "romanised": "Naeryo Chagi",
        "hangul": "내려차기"
      },
      "description": "A downward striking kick where the leg is raised high and brought down forcefully onto the target, striking with the heel or back heel.",
      "execution": {
        "chamber": "Raise leg straight up as high as possible",
        "strike": "Drive heel downward with force onto target",
        "retraction": "Control descent and prepare for next technique"
      },
      "striking_tool": {
        "hangul": "뒷축",
        "romanised": "Dwitchook",
        "english": "Back Heel",
        "phonetic": "/twit.tʃʰuk/"
      },
      "target_areas": [
        "crown of head",
        "shoulder",
        "collar bone",
        "forearm"
      ],
      "applicable_stances": [
        "gunnun_sogi",
        "narani_junbi_sogi"
      ],
      "belt_levels": [
        "2nd_keup",
        "1st_keup",
        "1st_dan",
        "2nd_dan"
      ],
      "difficulty": "advanced",
      "tags": [
        "downward",
        "axe",
        "heel",
        "overhead",
        "powerful"
      ],
      "variations": [
        "twimyo_naeryo_chagi"
      ],
      "images": [
        "naeryo_chagi_chamber.jpg",
        "naeryo_chagi_peak.jpg",
        "naeryo_chagi_impact.jpg"
      ],
      "common_mistakes": [
        "Not raising leg high enough",
        "Poor control on descent",
        "Wrong striking surface"
      ]
    },
    {
      "id": "kick_flying_front_kick",
      "names": {
        "english": "Flying Front Kick",
        "romanised": "Twimyo Ap Chagi",
        "hangul": "뛰며 앞 차기"
      },
      "category": "kicks"
    },
    {
      "id": "kick_flying_high_kick",
      "names": {
        "english": "Flying High Kick",
        "romanised": "Twimyo Nopi Chagi",
        "hangul": "뛰며 높이 차기"
      },
      "category": "kicks"
    },
    {
      "id": "twimyo_chagi",
      "names": {
        "english": "Flying Kick",
        "phonetic": "/tʃwi.mjʌ.tʃʰa.ɡi/",
        "romanised": "Twimyo Chagi",
        "hangul": "뛰며차기"
      },
      "description": "Any kick performed while airborne. Can be combined with various kick types such as front kick, side kick, or turning kick to increase power and reach.",
      "execution": {
        "chamber": "Jump into air while chambering leg",
        "strike": "Execute chosen kick while airborne",
        "landing": "Land in balanced stance ready for next technique"
      },
      "striking_tool": {
        "hangul": "다양함",
        "romanised": "Various",
        "english": "Varies by kick type",
        "phonetic": "/ta.jaŋ.ham/"
      },
      "target_areas": [
        "head",
        "chest",
        "solar plexus"
      ],
      "applicable_stances": [
        "gunnun_sogi",
        "narani_junbi_sogi"
      ],
      "belt_levels": [
        "2nd_keup",
        "1st_keup",
        "1st_dan",
        "2nd_dan"
      ],
      "difficulty": "advanced",
      "tags": [
        "jumping",
        "airborne",
        "dynamic",
        "power"
      ],
      "variations": [
        "twimyo_yop_chagi",
        "twimyo_dollyo_chagi"
      ],
      "images": [
        "twimyo_chagi_takeoff.jpg",
        "twimyo_chagi_airborne.jpg",
        "twimyo_chagi_landing.jpg"
      ],
      "common_mistakes": [
        "Poor timing",
        "Bad landing",
        "Loss of power in air"
      ]
    },
    {
      "id": "twimyo_yop_chagi",
      "names": {
        "english": "Flying Side Kick",
        "phonetic": "/tʃwi.mjʌ.jʌp.tʃʰa.ɡi/",
        "romanised": "Twimyo Yop Chagi",
        "hangul": "뛰며옭차기"
      },
      "description": "A jumping side kick performed while airborne, combining the power of a jump with the penetrating force of a side kick.",
      "execution": {
        "chamber": "Jump while chambering leg across body",
        "strike": "Execute side kick while in air using footsword",
        "landing": "Land in controlled stance"
      },
      "striking_tool": {
        "hangul": "발칼",
        "romanised": "Balkal",
        "english": "Footsword",
        "phonetic": "/pal.kʰal/"
      },
      "target_areas": [
        "head",
        "chest",
        "ribs"
      ],
      "applicable_stances": [
        "gunnun_sogi",
        "narani_junbi_sogi"
      ],
      "belt_levels": [
        "2nd_keup",
        "1st_keup",
        "1st_dan",
        "2nd_dan"
      ],
      "difficulty": "advanced",
      "tags": [
        "jumping",
        "side",
        "flying",
        "powerful"
      ],
      "variations": [
        "twimyo_chagi"
      ],
      "images": [
        "twimyo_yop_takeoff.jpg",
        "twimyo_yop_execution.jpg",
        "twimyo_yop_landing.jpg"
      ],
      "common_mistakes": [
        "Poor takeoff",
        "Wrong foot angle",
        "Hard landing"
      ]
    },
    {
      "id": "kick_flying_side_piercing_kick",
      "names": {
        "english": "Flying Side Piercing Kick",
        "romanised": "Twimyo Yop Cha Jirugi",
        "hangul": "뛰며 옆 차 지르기"
      },
      "category": "kicks"
    },
    {
      "id": "kick_flying_side_thrusting_kick",
      "names": {
        "english": "Flying Side Thrusting Kick",
        "romanised": "Twimyo Yop Cha Tulgi",
        "hangul": "뛰며 옆 차 틀기"
      },
      "category": "kicks"
    },
    {
      "id": "kick_flying_turning_kick",
      "names": {
        "english": "Flying turning Kick",
        "romanised": "Twimyo Dollyo Chagi",
        "hangul": "뛰며 돌려 차기"
      },
      "category": "kicks"
    },
    {
      "id": "kick_flying_twisting_kick",
      "names": {
        "english": "Flying Twisting Kick",
        "romanised": "Twimyo Bituro Chagi",
        "hangul": "뛰며 비트로 차기"
      },
      "category": "kicks"
    },
    {
      "id": "kick_flying_two_direction_kick_split_kick",
      "names": {
        "english": "Flying Two Direction Kick",
        "romanised": "Twimyo Sangbang Chagi",
        "hangul": "뛰며 상방 차기"
      },
      "category": "kicks"
    },
    {
      "id": "ap_cha_busigi",
      "names": {
        "english": "Front Snap Kick",
        "phonetic": "/ap.tʃʰa.bu.ɕi.ɡi/",
        "romanised": "Ap Cha Busigi",
        "hangul": "앙차부시기"
      },
      "description": "A basic linear kick executed by raising the knee and extending the foot forward, striking with the ball of the foot. The knee should be brought up first, then the foot extended forward in a snapping motion.",
      "execution": {
        "chamber": "Lift knee to waist height, keeping foot close to body",
        "strike": "Extend foot forward with ball of foot as striking surface",
        "retraction": "Pull foot back to chambered position before placing down"
      },
      "striking_tool": {
        "hangul": "앞꿈치",
        "romanised": "Apkumchi",
        "english": "Ball of Foot",
        "phonetic": "/ap.k͈um.tʃʰi/"
      },
      "target_areas": [
        "solar plexus",
        "abdomen",
        "chest",
        "groin"
      ],
      "applicable_stances": [
        "gunnun_sogi",
        "narani_junbi_sogi",
        "ap_koobi_seogi"
      ],
      "belt_levels": [
        "8th_keup",
        "7th_keup",
        "6th_keup",
        "5th_keup",
        "4th_keup",
        "3rd_keup",
        "2nd_keup",
        "1st_keup",
        "1st_dan",
        "2nd_dan"
      ],
      "difficulty": "basic",
      "tags": [
        "linear",
        "front",
        "snap",
        "basic",
        "fundamental"
      ],
      "variations": [
        "ap_cha_olligi"
      ],
      "images": [
        "ap_cha_busigi_chamber.jpg",
        "ap_cha_busigi_execution.jpg",
        "ap_cha_busigi_target.jpg"
      ],
      "common_mistakes": [
        "Not chambering knee high enough",
        "Using instep instead of ball of foot",
        "Leaning back too much"
      ]
    },
    {
      "id": "golcho_chagi",
      "names": {
        "english": "Hooking Kick",
        "phonetic": "/ɡol.tʃʰo.tʃʰa.ɡi/",
        "romanised": "Golcho Chagi",
        "hangul": "굴추차기"
      },
      "description": "A hooking kick that starts like a side kick but curves inward at the end, striking with the back heel. The foot hooks around to strike the side or back of the target.",
      "execution": {
        "chamber": "Chamber leg like a side kick",
        "strike": "Extend as side kick then hook foot inward",
        "retraction": "Reverse the hooking motion back to chamber"
      },
      "striking_tool": {
        "hangul": "뒷축",
        "romanised": "Dwitchook",
        "english": "Back Heel",
        "phonetic": "/twit.tʃʰuk/"
      },
      "target_areas": [
        "jaw",
        "temple",
        "neck",
        "kidney"
      ],
      "applicable_stances": [
        "gunnun_sogi",
        "narani_junbi_sogi"
      ],
      "belt_levels": [
        "2nd_keup",
        "1st_keup",
        "1st_dan",
        "2nd_dan"
      ],
      "difficulty": "advanced",
      "tags": [
        "hooking",
        "curved",
        "heel",
        "deceptive"
      ],
      "variations": [
        "bandae_dollyo_goro_chagi"
      ],
      "images": [
        "golcho_chagi_chamber.jpg",
        "golcho_chagi_hook.jpg",
        "golcho_chagi_impact.jpg"
      ],
      "common_mistakes": [
        "Not hooking enough",
        "Poor timing",
        "Wrong foot position"
      ]
    },
    {
      "id": "kick_inward_crescent_kick",
      "names": {
        "english": "Inward Crescent Kick",
        "romanised": "Anaero Bandal Chagi",
        "hangul": "안으로 반달 차기"
      },
      "category": "kicks"
    },
    {
      "id": "moorup_chagi",
      "names": {
        "english": "Knee Kick",
        "phonetic": "/mu.ɾɯp.tʃʰa.ɡi/",
        "romanised": "Moorup Chagi",
        "hangul": "무릎차기"
      },
      "description": "A close-range attack using the knee as the striking surface, typically delivered in an upward motion into the opponent's midsection or ribs.",
      "execution": {
        "chamber": "Bring knee up toward target",
        "strike": "Drive knee upward into target area",
        "retraction": "Lower leg back to starting position"
      },
      "striking_tool": {
        "hangul": "무릎",
        "romanised": "Moorup",
        "english": "Knee",
        "phonetic": "/mu.ɾɯp/"
      },
      "target_areas": [
        "solar plexus",
        "ribs",
        "abdomen",
        "groin"
      ],
      "applicable_stances": [
        "gunnun_sogi",
        "narani_junbi_sogi",
        "ap_koobi_seogi"
      ],
      "belt_levels": [
        "5th_keup",
        "4th_keup",
        "3rd_keup",
        "2nd_keup",
        "1st_keup",
        "1st_dan",
        "2nd_dan"
      ],
      "difficulty": "basic",
      "tags": [
        "knee",
        "close_range",
        "upward",
        "clinch"
      ],
      "variations": [
        "twimyo_moorup_chagi"
      ],
      "images": [
        "moorup_chagi_chamber.jpg",
        "moorup_chagi_impact.jpg",
        "moorup_chagi_clinch.jpg"
      ],
      "common_mistakes": [
        "Too much distance",
        "Poor hip drive",
        "Wrong angle of attack"
      ]
    },
    {
      "id": "kick_knee_low_front_snap_kick",
      "names": {
        "english": "Knee Low Front Snap Kick",
        "romanised": "Moorup Ap Cha Busigi",
        "hangul": "무릎 앞 차 부시기"
      },
      "category": "kicks"
    },
    {
      "id": "kick_outward_crescent_kick",
      "names": {
        "english": "Outward Crescent Kick",
        "romanised": "Bakaero Bandal Chagi",
        "hangul": "바깥으로 반달 차기"
      },
      "category": "kicks"
    },
    {
      "id": "bandae_dollyo_goro_chagi",
      "names": {
        "english": "Reverse Hook Kick",
        "phonetic": "/pan.de.dol.ljʌ.ɡʌl.lo.tʃʰa.ɡi/",
        "romanised": "Bandae Dollyo Goro Chagi",
        "hangul": "반대돌려걸로차기"
      },
      "description": "Hook kick performed in reverse direction - an advanced spinning technique for surprise attacks and counter-attacks that is difficult for opponents to anticipate due to the reverse rotation.",
      "execution": {
        "chamber": "Start from fighting stance, pivot on supporting foot while beginning body rotation",
        "kick": "Rotate body 180-360 degrees, extend kicking leg in hooking motion, strike with heel",
        "recovery": "Complete rotation while maintaining balance, return to fighting stance"
      },
      "striking_tool": {
        "hangul": "뒤꿈치",
        "romanised": "Dwikkumchi",
        "english": "Heel",
        "phonetic": "/twi.k͈ɯm.tʃʰi/"
      },
      "target_areas": [
        "head",
        "temple",
        "jaw",
        "ribs"
      ],
      "applicable_stances": [
        "gunnun_sogi",
        "narani_junbi_sogi"
      ],
      "belt_levels": [
        "2nd_keup",
        "1st_keup",
        "1st_dan",
        "2nd_dan"
      ],
      "difficulty": "advanced",
      "tags": [
        "advanced",
        "circular",
        "spinning",
        "counter_attack",
        "deceptive",
        "hook"
      ],
      "variations": [
        "twimyo_bandae_dollyo_goro_chagi"
      ],
      "images": [
        "bandae_dollyo_goro_setup.jpg",
        "bandae_dollyo_goro_spin.jpg",
        "bandae_dollyo_goro_hook.jpg"
      ],
      "common_mistakes": [
        "Loss of balance during spin",
        "Improper heel positioning",
        "Dropping guard during rotation"
      ]
    },
    {
      "id": "kick_reverse_hooking_kick",
      "names": {
        "english": "Reverse Hooking Kick",
        "romanised": "Bandae Golcho Chagi",
        "hangul": "반대 걸차 차기"
      },
      "category": "kicks"
    },
    {
      "id": "bandae_dollyo_chagi",
      "names": {
        "english": "Reverse Turning Kick",
        "phonetic": "/pan.de.dol.ljʌ.tʃʰa.ɡi/",
        "romanised": "Bandae Dollyo Chagi",
        "hangul": "반대돌려차기"
      },
      "description": "A reverse circular kick executed by spinning the body in the opposite direction of a regular turning kick, striking with the back heel. Creates deceptive timing and power.",
      "execution": {
        "chamber": "Pivot on supporting foot, turning body away from target",
        "strike": "Complete spin while extending heel toward target",
        "retraction": "Control landing and prepare for follow-up"
      },
      "striking_tool": {
        "hangul": "뒷축",
        "romanised": "Dwitchook",
        "english": "Back Heel",
        "phonetic": "/twit.tʃʰuk/"
      },
      "target_areas": [
        "head",
        "temple",
        "jaw",
        "ribs"
      ],
      "applicable_stances": [
        "gunnun_sogi",
        "narani_junbi_sogi"
      ],
      "belt_levels": [
        "5th_keup",
        "4th_keup",
        "3rd_keup",
        "2nd_keup",
        "1st_keup",
        "1st_dan",
        "2nd_dan"
      ],
      "difficulty": "advanced",
      "tags": [
        "reverse",
        "spinning",
        "circular",
        "heel",
        "deceptive"
      ],
      "variations": [
        "bandae_dollyo_goro_chagi"
      ],
      "images": [
        "bandae_dollyo_setup.jpg",
        "bandae_dollyo_spin.jpg",
        "bandae_dollyo_impact.jpg"
      ],
      "common_mistakes": [
        "Incomplete rotation",
        "Poor balance",
        "Wrong striking surface"
      ]
    },
    {
      "id": "ap_cha_olligi",
      "names": {
        "english": "Rising Kick",
        "phonetic": "/ap.tʃʰa.ol.li.ɡi/",
        "romanised": "Ap Cha Olligi",
        "hangul": "앙차올리기"
      },
      "description": "The fundamental kick in Taekwondo - an upward kicking motion performed as both stretching and power development exercise. Executed as 3-count movement with chamber, extension, and recovery phases.",
      "execution": {
        "chamber": "Chamber the kick while performing guarding block, striking leg fully drawn back",
        "kick": "Rise up with ball of foot, extending kick with hip engagement to target",
        "recovery": "Re-chamber the kick and return to ready position (3-count execution)"
      },
      "striking_tool": {
        "hangul": "앞꿈치",
        "romanised": "Apkumchi",
        "english": "Ball of Foot",
        "phonetic": "/ap.kɯm.tʃʰi/"
      },
      "target_areas": [
        "groin",
        "chin",
        "face"
      ],
      "applicable_stances": [
        "narani_junbi_sogi",
        "gunnun_sogi"
      ],
      "belt_levels": [
        "10th_keup",
        "9th_keup",
        "8th_keup",
        "7th_keup",
        "6th_keup",
        "5th_keup",
        "4th_keup",
        "3rd_keup",
        "2nd_keup",
        "1st_keup",
        "1st_dan",
        "2nd_dan"
      ],
      "difficulty": "basic",
      "tags": [
        "fundamental",
        "linear",
        "stretching",
        "power_development",
        "first_kick"
      ],
      "variations": [
        "twimyo_ap_cha_olligi"
      ],
      "images": [
        "ap_cha_olligi_chamber.jpg",
        "ap_cha_olligi_extension.jpg",
        "ap_cha_olligi_recovery.jpg"
      ],
      "common_mistakes": [
        "Swinging leg without hip engagement",
        "Poor chamber position",
        "Loss of balance"
      ]
    },
    {
      "id": "yop_cha_jirugi",
      "names": {
        "english": "Side Piercing Kick",
        "phonetic": "/jʌp.tʃʰa.tʃi.ɾɯ.ɡi/",
        "romanised": "Yop Cha Jirugi",
        "hangul": "옭차지르기"
      },
      "description": "A penetrating side kick delivered with thrusting motion, striking with the footsword to pierce through the target.",
      "execution": {
        "chamber": "Lift knee across body to waist height",
        "strike": "Thrust footsword directly into target with piercing motion",
        "retraction": "Pull foot back to chamber maintaining balance"
      },
      "striking_tool": {
        "hangul": "발칼",
        "romanised": "Balkal",
        "english": "Footsword",
        "phonetic": "/pal.kʰal/"
      },
      "target_areas": [
        "ribs",
        "solar plexus",
        "kidney"
      ],
      "applicable_stances": [
        "gunnun_sogi",
        "narani_junbi_sogi"
      ],
      "belt_levels": [
        "2nd_keup",
        "1st_keup",
        "1st_dan",
        "2nd_dan"
      ],
      "difficulty": "advanced",
      "tags": [
        "side",
        "piercing",
        "thrusting",
        "footsword"
      ],
      "variations": [
        "twimyo_yop_cha_jirugi"
      ],
      "images": [
        "yop_cha_jirugi_chamber.jpg",
        "yop_cha_jirugi_thrust.jpg",
        "yop_cha_jirugi_pierce.jpg"
      ],
      "common_mistakes": [
        "Not enough thrust",
        "Wrong foot angle",
        "Poor balance"
      ]
    },
    {
      "id": "kick_side_rising_kick",
      "names": {
        "english": "Side Rising Kick",
        "romanised": "Yop Cha Olligi",
        "hangul": "옆 차 올리기"
      },
      "category": "kicks"
    },
    {
      "id": "kick_side_thrusting_kick",
      "names": {
        "english": "Side Thrusting Kick",
        "romanised": "Yop Cha Tulgi",
        "hangul": "옆 차 틀기"
      },
      "category": "kicks"
    },
    {
      "id": "kick_stamping_kick",
      "names": {
        "english": "Stamping Kick",
        "romanised": "Cha Busigi",
        "hangul": "차 부시기"
      },
      "category": "kicks"
    },
    {
      "id": "kick_sweeping_kick",
      "names": {
        "english": "Sweeping Kick",
        "romanised": "Goro Chagi",
        "hangul": "고로 차기"
      },
      "category": "kicks"
    },
    {
      "id": "dollyo_chagi",
      "names": {
        "english": "Turning Kick",
        "phonetic": "/tol.ɾjʌ.tʃʰa.ɡi/",
        "romanised": "Dollyo Chagi",
        "hangul": "돌려차기"
      },
      "description": "A circular kick that travels in an arc, striking with the ball of the foot or instep. The hip rotates to generate power as the leg sweeps in a circular motion to the target.",
      "execution": {
        "chamber": "Lift knee to side, keeping foot close to body",
        "strike": "Rotate hip and extend foot in circular arc to target",
        "retraction": "Pull foot back along same circular path to chamber"
      },
      "striking_tool": {
        "hangul": "앞꿈치",
        "romanised": "Apkumchi",
        "english": "Ball of Foot",
        "phonetic": "/ap.k͈um.tʃʰi/"
      },
      "target_areas": [
        "temple",
        "jaw",
        "ribs",
        "liver",
        "head"
      ],
      "applicable_stances": [
        "gunnun_sogi",
        "narani_junbi_sogi",
        "ap_koobi_seogi"
      ],
      "belt_levels": [
        "8th_keup",
        "7th_keup",
        "6th_keup",
        "5th_keup",
        "4th_keup",
        "3rd_keup",
        "2nd_keup",
        "1st_keup",
        "1st_dan",
        "2nd_dan"
      ],
      "difficulty": "intermediate",
      "tags": [
        "circular",
        "turning",
        "rotation",
        "hip",
        "arc"
      ],
      "variations": [
        "bandae_dollyo_chagi"
      ],
      "images": [
        "dollyo_chagi_chamber.jpg",
        "dollyo_chagi_rotation.jpg",
        "dollyo_chagi_impact.jpg"
      ],
      "common_mistakes": [
        "Not rotating hip enough",
        "Poor chamber position",
        "Losing balance during rotation"
      ]
    },
    {
      "id": "kick_twisting_kick",
      "names": {
        "english": "Twisting Kick",
        "romanised": "Bituro Chagi",
        "hangul": "비트로 차기"
      },
      "category": "kicks"
    },
    {
      "id": "kick_vertical_kick",
      "names": {
        "english": "Vertical Kick",
        "romanised": "Sewo Chagi",
        "hangul": "세워 차기"
      },
      "category": "kicks"
    }
  ]
}
